[{
  "dateTime" : "01/15/14 00:00:00",
  "value" : "62"
},{
  "dateTime" : "01/16/14 00:00:00",
  "value" : "37"
},{
  "dateTime" : "01/17/14 00:00:00",
  "value" : "73"
},{
  "dateTime" : "01/18/14 00:00:00",
  "value" : "0"
},{
  "dateTime" : "01/19/14 00:00:00",
  "value" : "65"
},{
  "dateTime" : "01/20/14 00:00:00",
  "value" : "65"
},{
  "dateTime" : "01/21/14 00:00:00",
  "value" : "35"
},{
  "dateTime" : "01/22/14 00:00:00",
  "value" : "5"
},{
  "dateTime" : "01/23/14 00:00:00",
  "value" : "1"
},{
  "dateTime" : "01/24/14 00:00:00",
  "value" : "3"
},{
  "dateTime" : "01/25/14 00:00:00",
  "value" : "3"
},{
  "dateTime" : "01/26/14 00:00:00",
  "value" : "14"
},{
  "dateTime" : "01/27/14 00:00:00",
  "value" : "64"
},{
  "dateTime" : "01/28/14 00:00:00",
  "value" : "87"
},{
  "dateTime" : "01/29/14 00:00:00",
  "value" : "3"
},{
  "dateTime" : "01/30/14 00:00:00",
  "value" : "67"
},{
  "dateTime" : "01/31/14 00:00:00",
  "value" : "66"
},{
  "dateTime" : "02/01/14 00:00:00",
  "value" : "3"
},{
  "dateTime" : "02/02/14 00:00:00",
  "value" : "70"
},{
  "dateTime" : "02/03/14 00:00:00",
  "value" : "1"
},{
  "dateTime" : "02/04/14 00:00:00",
  "value" : "2"
},{
  "dateTime" : "02/05/14 00:00:00",
  "value" : "4"
},{
  "dateTime" : "02/06/14 00:00:00",
  "value" : "67"
},{
  "dateTime" : "02/07/14 00:00:00",
  "value" : "3"
},{
  "dateTime" : "02/08/14 00:00:00",
  "value" : "1"
},{
  "dateTime" : "02/09/14 00:00:00",
  "value" : "65"
},{
  "dateTime" : "02/10/14 00:00:00",
  "value" : "58"
},{
  "dateTime" : "02/11/14 00:00:00",
  "value" : "3"
},{
  "dateTime" : "02/12/14 00:00:00",
  "value" : "4"
},{
  "dateTime" : "02/13/14 00:00:00",
  "value" : "68"
}]